jobrunner/__init__.py
jobrunner/__main__.py
jobrunner/cli.py
jobrunner/exceptions.py
jobrunner/plugins.py
jobrunner/analysis/__init__.py
jobrunner/analysis/graph.py
jobrunner/config/__init__.py
jobrunner/config/loader.py
jobrunner/config/models.py
jobrunner/core/__init__.py
jobrunner/core/executor.py
jobrunner/core/parallel.py
jobrunner/core/resolver.py
jobrunner/execution/__init__.py
jobrunner/execution/context.py
jobrunner/execution/result.py
jobrunner/execution/runner.py
jobrunner/integrations/__init__.py
jobrunner/integrations/env.py
jobrunner/integrations/git.py
jobrunner/output/__init__.py
jobrunner/output/formatter.py
jobrunner/output/progress.py
jobrunner/output/reporter.py
jobrunner/rendering/__init__.py
jobrunner/rendering/templates.py
jobrunner/utils/__init__.py
jobrunner/utils/cache.py
jobrunner/utils/shell.py
deprun-0.5.0.dist-info/METADATA
deprun-0.5.0.dist-info/WHEEL
deprun-0.5.0.dist-info/entry_points.txt
deprun-0.5.0.dist-info/licenses/LICENSE
deprun-0.5.0.dist-info/RECORD
