Metadata-Version: 2.4
Name: deprun
Version: 0.5.0
Summary: A modern Python task automation and multi-repository orchestration tool
Project-URL: Homepage, https://gitlab.com/proj_amx_01/tools/job-runner
Project-URL: Documentation, https://gitlab.com/proj_amx_01/tools/job-runner/-/blob/main/README.md
Project-URL: Repository, https://gitlab.com/proj_amx_01/tools/job-runner
Project-URL: Issues, https://gitlab.com/proj_amx_01/tools/job-runner/-/issues
Author-email: Peter De Herdt <peter.deherdt@softathome.com>
License: MIT
License-File: LICENSE
Keywords: automation,build,git,orchestration,tasks
Classifier: Development Status :: 3 - Alpha
Classifier: Intended Audience :: Developers
Classifier: License :: OSI Approved :: MIT License
Classifier: Programming Language :: Python :: 3
Classifier: Programming Language :: Python :: 3.9
Classifier: Programming Language :: Python :: 3.10
Classifier: Programming Language :: Python :: 3.11
Classifier: Programming Language :: Python :: 3.12
Requires-Python: >=3.9
Requires-Dist: click>=8.1.0
Requires-Dist: pydantic>=2.0.0
Requires-Dist: pyyaml>=6.0.0
Requires-Dist: rich>=13.0.0
Provides-Extra: dev
Requires-Dist: black>=23.0.0; extra == 'dev'
Requires-Dist: mypy>=1.5.0; extra == 'dev'
Requires-Dist: pytest-cov>=4.1.0; extra == 'dev'
Requires-Dist: pytest-mock>=3.11.0; extra == 'dev'
Requires-Dist: pytest>=7.4.0; extra == 'dev'
Requires-Dist: ruff>=0.1.0; extra == 'dev'
Provides-Extra: docs
Requires-Dist: mkdocs-material>=9.4.0; extra == 'docs'
Requires-Dist: mkdocs>=1.5.0; extra == 'docs'
